cstop/__init__.py
cstop/core.py
cstop-1.0.0.post1.dist-info/DESCRIPTION.rst
cstop-1.0.0.post1.dist-info/METADATA
cstop-1.0.0.post1.dist-info/RECORD
cstop-1.0.0.post1.dist-info/WHEEL
cstop-1.0.0.post1.dist-info/entry_points.txt
cstop-1.0.0.post1.dist-info/metadata.json
cstop-1.0.0.post1.dist-info/top_level.txt
