Metadata-Version: 2.0
Name: cstop
Version: 1.0.0.post1
Summary: Simple CLI stopwatch
Home-page: https://exhuma.github.com/cstop
Author: Michel Albert
Author-email: michel@albert.lu
License: BSD
Platform: UNKNOWN
